{"stats":{"minecraft:used":{"minecraft:oak_trapdoor":1,"minecraft:water_bucket":548,"minecraft:writable_book":2,"minecraft:iron_bars":95,"minecraft:iron_shovel":84,"minecraft:flint_and_steel":4,"minecraft:stone_pickaxe":4,"minecraft:polished_andesite":33,"minecraft:spruce_slab":1,"minecraft:stone_shovel":26,"minecraft:redstone":5,"minecraft:oak_sign":2,"minecraft:spruce_planks":1,"minecraft:stone":5,"minecraft:cracked_stone_bricks":15,"minecraft:smooth_quartz_stairs":8,"minecraft:dirt":35,"minecraft:tnt":2,"minecraft:white_bed":3,"minecraft:painting":5,"minecraft:gray_concrete":26,"minecraft:redstone_torch":4,"minecraft:stone_brick_slab":17,"minecraft:lever":3,"minecraft:diamond_pickaxe":1,"minecraft:black_concrete":110,"minecraft:command_block":6,"minecraft:light_gray_concrete":6,"minecraft:grass_block":43,"minecraft:iron_pickaxe":44,"minecraft:stone_button":4,"minecraft:smooth_quartz":21,"minecraft:iron_door":3,"minecraft:diorite_wall":1,"minecraft:gravel":3,"minecraft:stone_brick_stairs":4,"minecraft:stone_bricks":192,"minecraft:item_frame":1,"minecraft:chiseled_stone_bricks":2,"minecraft:diamond_sword":1,"minecraft:repeater":2,"minecraft:black_stained_glass":3,"minecraft:written_book":43,"minecraft:iron_trapdoor":1,"minecraft:repeating_command_block":32,"minecraft:smooth_stone_slab":6,"minecraft:stone_pressure_plate":4,"minecraft:air":72228,"minecraft:cobweb":1,"minecraft:golden_pickaxe":4,"minecraft:splash_potion":24},"minecraft:killed":{"minecraft:bat":1},"minecraft:broken":{"minecraft:stone_pickaxe":1,"minecraft:iron_shovel":7,"minecraft:shears":2,"minecraft:iron_pickaxe":12,"minecraft:stone_shovel":1},"minecraft:picked_up":{"minecraft:iron_trapdoor":1,"minecraft:light_gray_shulker_box":1,"minecraft:dirt":2,"minecraft:stone_stairs":1,"minecraft:stone_bricks":1,"minecraft:cracked_stone_bricks":11,"minecraft:detector_rail":1,"minecraft:redstone_torch":1,"minecraft:glowstone_dust":6,"minecraft:stick":2,"minecraft:stone_brick_slab":1,"minecraft:iron_hoe":1,"minecraft:polished_andesite":2,"minecraft:light_gray_bed":47,"minecraft:black_concrete":1,"minecraft:iron_block":1,"minecraft:painting":1,"minecraft:iron_bars":2},"minecraft:custom":{"minecraft:inspect_dropper":4,"minecraft:mob_kills":1,"minecraft:inspect_hopper":49,"minecraft:open_barrel":73,"minecraft:fill_cauldron":1,"minecraft:play_one_minute":3241992,"minecraft:open_shulker_box":182,"minecraft:pot_flower":3,"minecraft:leave_game":43,"minecraft:time_since_death":139,"minecraft:sleep_in_bed":7,"minecraft:climb_one_cm":13468,"minecraft:time_since_rest":165,"minecraft:sprint_one_cm":769893,"minecraft:damage_taken":310,"minecraft:walk_one_cm":7619178,"minecraft:trigger_trapped_chest":10,"minecraft:drop":6,"minecraft:damage_dealt":68,"minecraft:swim_one_cm":53909,"minecraft:fly_one_cm":21584364,"minecraft:open_chest":53,"minecraft:crouch_one_cm":223623,"minecraft:deaths":17,"minecraft:sneak_time":141178,"minecraft:walk_under_water_one_cm":61983,"minecraft:jump":9956,"minecraft:interact_with_blast_furnace":3,"minecraft:walk_on_water_one_cm":268855,"minecraft:interact_with_smoker":2,"minecraft:fall_one_cm":6570,"minecraft:inspect_dispenser":68},"minecraft:dropped":{"minecraft:stone_stairs":1,"minecraft:polished_andesite":2,"minecraft:dirt":1,"minecraft:iron_bars":1,"minecraft:stone_brick_slab":1},"minecraft:mined":{"minecraft:white_bed":22,"minecraft:cobblestone_stairs":2,"minecraft:grass_block":35,"minecraft:andesite_slab":1,"minecraft:white_stained_glass":5,"minecraft:light_gray_bed":9,"minecraft:cobblestone":2,"minecraft:coarse_dirt":5,"minecraft:brown_concrete_powder":52,"minecraft:glowstone":2,"minecraft:light_gray_stained_glass":3,"minecraft:cobblestone_slab":2,"minecraft:dirt":16,"minecraft:cracked_stone_bricks":37,"minecraft:stone":4,"minecraft:redstone_lamp":4}},"DataVersion":1976}